slap/__init__.py
slap/api.py
slap/cli.py
slap/config.py
slap/config_builder.py
slap/esri.py
slap/git.py
slap/publisher.py
slap/auth/__init__.py
slap/auth/token.py
slap/config/__init__.py
slap/config/builder.py
slap/config/parser.py
slap-3.3.1.dist-info/DESCRIPTION.rst
slap-3.3.1.dist-info/METADATA
slap-3.3.1.dist-info/RECORD
slap-3.3.1.dist-info/WHEEL
slap-3.3.1.dist-info/entry_points.txt
slap-3.3.1.dist-info/metadata.json
slap-3.3.1.dist-info/top_level.txt
tests/auth/__init__.py
tests/auth/test_token.py
tests/config/__init__.py
tests/config/test_builder.py
tests/config/test_parser.py
